jdif/__init__.py
jdif/display.py
jdif-4.6.2.dist-info/LICENSE
jdif-4.6.2.dist-info/METADATA
jdif-4.6.2.dist-info/WHEEL
jdif-4.6.2.dist-info/entry_points.txt
jdif-4.6.2.dist-info/top_level.txt
jdif-4.6.2.dist-info/RECORD
