Metadata-Version: 2.1
Name: jdif
Version: 4.6.2
Summary: To find json differences on CLI
Author: shivani
License: MIT
Project-URL: Source, https://github.com/Shivani-20/json-diff-cli
Keywords: json,diff
Classifier: Programming Language :: Python :: 3.12
Classifier: License :: OSI Approved :: MIT License
Classifier: Operating System :: Microsoft :: Windows
Classifier: Intended Audience :: Developers
Classifier: Topic :: File Formats :: JSON
Classifier: Topic :: File Formats :: JSON :: JSON Schema
Classifier: Topic :: Software Development :: Debuggers
Classifier: Environment :: Console
Requires-Python: >=3.10
License-File: LICENSE
Requires-Dist: termcolor>=2.4.0
Requires-Dist: deepdiff>=7.0.1
Requires-Dist: charade>=1.0.3
Requires-Dist: pyparsing>=3.1.2
